poll/__init__.py
poll-1.0.dist-info/DESCRIPTION.rst
poll-1.0.dist-info/METADATA
poll-1.0.dist-info/metadata.json
poll-1.0.dist-info/RECORD
poll-1.0.dist-info/top_level.txt
poll-1.0.dist-info/WHEEL
